JVM 中的同步是基于进入与退出监视器对象（管程对象）（Monitor）来实现的，每个对象的实例都会有一个 Monitor 对象，Monitor 对象会和 Java 对象已通创建并销毁。Monitor 对象是由 C++ 来实现的。

当多个线程同时访问一段同步代码时，这些线程会被放到一个 EntryList 集合中，处于阻塞状态的线程都会被放到该列表当中。接下来，当线程获取到对象的 Monitor 时，Monitor 是依赖于底层操作系统的 mutex lock 来实现互斥的，线程获取到 mutex 成功，则会持有该 mutex，这是其他线程就无法再获取到该 mutex。

如果线程调用了 wait 方法，那么该线程就会释放掉所有的 mutex，并且该线程会进入到 WaitSet 集合（等待集合）中，等待下一次被其他线程调用 notify/notifyAll 唤醒。如果当前线程顺利执行完毕方法，那么他也会释放掉所持有的 mutex。



总结一下：同步锁在这种实现方式当中，因为 Monitor 是依赖底层操作系统实现，这样就存在用户态与内核态之间的切换，所以会增加性能开销。

----

通过对象互斥锁的概念来保证共享数据操作的完整性。每个对象都对应于一个可称为『互斥锁』的标记，这个标记用于保证在任何时刻只有一个线程能访问该对象

那些处于 EntryList 与 WaitSet 中的线程均处于阻塞状态，阻塞操作是由操作系统来完成的，在 linux 下是通过 pthred_mutex_lock 函数来实现的。线程被阻塞后便会进入到内核调度状态，这回导致系统在用户态与内核态之间来回切换，验证影响锁的性能。

解决上述问题的办法便是自旋（Spin）。其原理是：当发生对 Monitor 的争用时，若 Owner 能够在很短的时间内释放掉锁，则那些正在征用的线程就可以稍微等待一下（即所谓的自旋），在 Owner 线程释放锁之后，争用线程可能会立刻获取到锁，从而避免了系统阻塞。不过，当 Owner 运行时间超过了临界值后，争用线程自旋一段时间后依然无法获取到锁，这是争用线程会停止自旋而进入到阻塞状态。所以总体的思想是：先自旋，不成功再进行阻塞，尽量保证降低阻塞的可能性，这对那些执行时间很短的代码块来说有极大的性能提升。显然，自旋在多处理器（多核心）上才有意义。











## 互斥锁的属性

1. PTHREAD_MUTEX_TIMED_NP：普通锁。这是缺省值。当一个线程加锁以后，其余请求锁的线程将会形成一个等待队列，并且在解锁后按照优先级获取到锁。这种策略可以确保资源的公平性。
2. PTHREAD_MUTEX_RECURSIVE_NP：嵌套锁。允许一个线程对同一个锁获取多次，并通过 unlock 解锁。如果是不同线程请求，则在加锁线程解锁时重新进行竞争。
3. PTHREAD_MUTEX_ERRORCHECK_NP：检错锁。如果一个线程请求同一个锁，则返回 EDEADLK，否则与PTHREAD_MUTEX_TIMED_NP 类型的动作相同，这样就保证了当不允许多次加锁时不会出现简单情况下的死锁。
4. PTHREAD_MUTEX_adaptive_NP：适应锁。动作最简单的锁类型，仅仅等待解锁后重新竞争



自旋（Spin）就是啥都不干，空转。



## 线程同步

在 jdk1.5 之前，我们若想实现线程同步，只能通过 synchronized 关键字来实现、底层 Java 也是通过 synchronized 关键字来做数据原子性维护的；synchronized 关键字是 JVM 实现的一种内置锁，从底层角度来说，这种锁的获取与释放都是由 JVM 隐式帮我们实现的。



从 jdk1.5 开始，并发包中引入了锁（Lock，接口），Lock 这种同步锁是基于 Java  来实现的，因此锁的获取与释放是通过 java 代码来实现的。然而 synchronized 是基于底层操作系统的 Mutex Lock 来实现的，每次对锁的获取与释放动作都会带来用户态与内核态之间的切换，这种切换会极大的增加系统的负担；所以在并发量较高时，也就是锁的竞争比较激烈的时候，synchronized 锁在性能上表现上就非常差。



从 jdk1.6 开始，synchronized 锁的实现发生了很大的变化；JVM 引入了相应的优化手段来提升 synchronized 锁的性能，这种提升涉及到偏向锁、轻量级锁及重量级锁等，从而减少锁的竞争锁带来的用户态与内核态之间的切换；这种锁的优化实际上是通过 Java 对象头中的一些标志位来实现的；对于锁的访问与改变实际上都与 Java 对象头息息相关。

从 jdk1.6 开始，对象实例在堆中会被划分成三个组成部分：对象头、实例数据与对齐填充。

对象头主要是由三块内容来构成：

1. Mark Word
2. 指向类的指针
3. 数组长度

其中 Mark Word（它记录了对象、锁及垃圾回收相关信息，在 64 为 JVM 中，其长度也是 64bit）的位信息包括了如下的组成部分：

1. 无锁标记
2. 偏向锁标记
3. 轻量级锁标记
4. 重量级锁标记
5. GC 标记

对于 synchronized 锁来说，锁的升级主要都是通过 Mark Word 中的锁标志位与是否是偏向锁标志位来达成的；synchronized 关键字所对应的锁都是先从偏向锁开始，随着锁竞争的不断升级，逐步演化至轻量级锁，最后则变成了重量级锁。

对于锁的演化来说，它会经历如下阶段

无锁 -> 偏向锁 -> 轻量级锁 -> 重量级锁



### 偏向锁

针对于一个线程来说的，它的主要作用就是优化同一个线程多次获取一个锁的情况；如果一个 synchronized 方法被一个线程访问，那么这个方法所在的对象就会在其 Mark Word 中的将偏向锁进行标记，同时还会有一个字段来存储该线程的 ID；当这个线程再次访问了同一个 synchronized 方法时，他会检查这个对象的 Mark Word 的偏向锁标记以及是否指向了其线程的 ID，如果是的话，那么该线程就无需再去进行管程（Monitor）了，而是直接进入到该方法体中。

如果是另一个线程访问这个 synchronized 方法时，那么实际情况会如何呢？偏向锁会被取消掉。



### 轻量级锁

若第一个线程已经获取到了当前对象的锁，这时第二个线程又开始尝试争抢该对象的锁，由于该对象的锁已经被第一个对象获取到，因此它是偏向锁。而第二个线程在争抢时，发现该对象的对象头中的 Mark Word 已经是偏向锁，但里面的线程 ID 并不是自己，那么他会进行 CAS（Compare and Swap），从而获取到锁，这里存在两个情况：

1. 获取锁成功：那么它会直接将 Mark Word 中的线程 ID 由第一个线程变更成自己（偏向锁标记位保持不变），这样该对象就会依然保持偏向锁的状态。
2. 获取锁失败：则表示这时可能会有多个线程同时在争抢该对象的锁，那么这时偏向锁就会进行升级，升级为轻量级锁。



自旋锁（轻量级锁的一种实现方式）

若自旋失败（依然无法获取到锁），那么锁就会转化成重量级锁，在这种情况下，无法获取到锁的线程都会进入到 Monitor（即内核态）

**自旋最大的特点就是避免了线程从用户态进入到内核态**



### 重量级锁

线程最终从用户态进入到了内核态。





## 编译器优化锁的措施

看下面一段代码

```java
public class MyTest2 {
    public Object object = new Object();
    public void method(){
        synchronized (object){ //同步锁
            System.out.println("hello world");
        }
    }
}
```

因为 object 类一个成员变量，它可以被多线程所共享。根据 javap -c 反编译出来的代码中是可以看到 monitorenter 和 monitorexit 这样的字节码的。因为 object 被多个线程所共享，那么它必然要发生锁的获取和释放，从这点上来看，是正常的。

```yml
public void method();
    Code:
       0: aload_0
       1: getfield      #3                  // Field object:Ljava/lang/Object;
       4: dup
       5: astore_1
       6: monitorenter  ## 获取锁
       7: getstatic     #4                  // Field java/lang/System.out:Ljava/io/PrintStream;
      10: ldc           #5                  // String hello world
      12: invokevirtual #6                  // Method java/io/PrintStream.println:(Ljava/lang/String;)V
      15: aload_1
      16: monitorexit  ## 退出锁
      17: goto          25
      20: astore_2
      21: aload_1
      22: monitorexit  ## 如果发生异常情况的退出
      23: aload_2
      24: athrow
      25: return
```

但是如果我们将代码稍作变更

```java
public class MyTest2 {
    public void method(){
        Object object = new Object();
        synchronized (object){
            System.out.println("hello world");
        }
    }
}
```

将 object 属性声明成了局部变量，那么这对于多线程来说，每个线程持有的 object 对象都是不同的。那么这个时候我们通过 javap -c 反编译出来的代码和上面一样。

显然这里的 synchronized 没有起到任何作用，但是编译过后的字节码并不会因为 synchronized 无作用而将 minitorenter 和 monitorexit 指令消除。但是无用的获取锁释放锁也是占用了资源，那么通过 JIT（Just In Time ）编译器可以很好的优化这样无效获取锁释放锁的情况。这种技术就叫做**锁消除**



### JIT编译器（Just In Time 编译器）

**1.锁消除**

JIT 编译器可以在动态编译同步代码时，使用一种叫做逃逸分析的技术，来通过该项技术判别程序中所使用的锁对象是否只被一个线程所使用，而没有散步到其他的线程当中；如果情况就是这样的话，那么 JIT 编译器在编译这个同步代码时就不会生成 synchronized 关键字锁标识的锁的申请与释放机器码，从而消除锁的使用流程。

**2.锁粗化**

```java
public class MyTest2 {
    private Object object = new Object();

    public void method(){
        synchronized (object){
            System.out.println("hello world");
        }
        synchronized (object){
            System.out.println("hello welcome");
        }
        synchronized (object){
            System.out.println("hello tom");
        }
    }
}
```

通过 javap -c 进行反编译还是会发现存在三次进入锁和释放锁的过程

```yaml
 public void method();
    Code:
       0: aload_0
       1: getfield      #3                  // Field object:Ljava/lang/Object;
       4: dup
       5: astore_1
       6: monitorenter   ## 第一次进入
       7: getstatic     #4                  // Field java/lang/System.out:Ljava/io/PrintStream;
      10: ldc           #5                  // String hello world
      12: invokevirtual #6                  // Method java/io/PrintStream.println:(Ljava/lang/String;)V
      15: aload_1
      16: monitorexit  ## 第一次退出
      17: goto          25
      20: astore_2
      21: aload_1
      22: monitorexit  ## 第一次异常退出
      23: aload_2
      24: athrow
      25: aload_0
      26: getfield      #3                  // Field object:Ljava/lang/Object;
      29: dup
      30: astore_1
      31: monitorenter  ## 第二次进入
      32: getstatic     #4                  // Field java/lang/System.out:Ljava/io/PrintStream;
      35: ldc           #7                  // String hello welcome
      37: invokevirtual #6                  // Method java/io/PrintStream.println:(Ljava/lang/String;)V
      40: aload_1
      41: monitorexit    ## 第二次退出
      42: goto          50
      45: astore_3
      46: aload_1
      47: monitorexit   ## 第二次异常退出
      48: aload_3
      49: athrow
      50: aload_0
      51: getfield      #3                  // Field object:Ljava/lang/Object;
      54: dup
      55: astore_1 
      56: monitorenter   ## 第三次进入
      57: getstatic     #4                  // Field java/lang/System.out:Ljava/io/PrintStream;
      60: ldc           #8                  // String hello tom
      62: invokevirtual #6                  // Method java/io/PrintStream.println:(Ljava/lang/String;)V
      65: aload_1
      66: monitorexit   ## 第三次退出
      67: goto          77
      70: astore        4
      72: aload_1
      73: monitorexit    ## 第三次异常退出
      74: aload         4
      76: athrow
      77: return
```

虽然三个 synchronized 都锁住了同一个对象，但是并不会影响字节码的结果。

但是 JIT 编译器会在动态编译时，会做出优化。它若发现前后相邻的 synchronized 块使用的是同一个锁对象，那么它就会把这几个 synchronized 块合并为一个较大的同步块，这样做的好处就在于线程在执行这些代码时就无须频繁申请与释放锁了，从而达到申请与释放锁一次，就可以执行完全部的同步代码块，从而提升了性能。这种优化就叫**锁粗化**













































































